odoo/addons/partner_multi_name/README.rst
odoo/addons/partner_multi_name/__init__.py
odoo/addons/partner_multi_name/__manifest__.py
odoo/addons/partner_multi_name/i18n/es CO.po
odoo/addons/partner_multi_name/i18n/es.po
odoo/addons/partner_multi_name/i18n/partner_multi_name.pot
odoo/addons/partner_multi_name/i18n/partner_other_names.pot
odoo/addons/partner_multi_name/models/__init__.py
odoo/addons/partner_multi_name/models/res_config_settings.py
odoo/addons/partner_multi_name/models/res_partner.py
odoo/addons/partner_multi_name/models/res_users.py
odoo/addons/partner_multi_name/static/description/icon.png
odoo/addons/partner_multi_name/tests/__init__.py
odoo/addons/partner_multi_name/tests/test_config.py
odoo/addons/partner_multi_name/tests/test_name.py
odoo/addons/partner_multi_name/tests/test_onchange.py
odoo/addons/partner_multi_name/views/res_partner_views.xml
odoo/addons/partner_multi_name/views/res_users_views.xml
odoo12_addon_partner_multi_name-12.0.1.0.1.dist-info/METADATA
odoo12_addon_partner_multi_name-12.0.1.0.1.dist-info/WHEEL
odoo12_addon_partner_multi_name-12.0.1.0.1.dist-info/top_level.txt
odoo12_addon_partner_multi_name-12.0.1.0.1.dist-info/RECORD
